{
	"configurations" : 
	[
		{
			"directories" : 
			[
				{
					"build" : ".",
					"childIndexes" : 
					[
						1,
						2
					],
					"jsonFile" : "directory-.-Debug-d0094a50bb2071803777.json",
					"minimumCMakeVersion" : 
					{
						"string" : "3.23"
					},
					"projectIndex" : 0,
					"source" : "."
				},
				{
					"build" : "app",
					"jsonFile" : "directory-app-Debug-7ab44524cbd5ada90c6a.json",
					"minimumCMakeVersion" : 
					{
						"string" : "3.23"
					},
					"parentIndex" : 0,
					"projectIndex" : 1,
					"source" : "app",
					"targetIndexes" : 
					[
						0
					]
				},
				{
					"build" : "engine",
					"jsonFile" : "directory-engine-Debug-776e2b00c6520ab49d05.json",
					"minimumCMakeVersion" : 
					{
						"string" : "3.23"
					},
					"parentIndex" : 0,
					"projectIndex" : 2,
					"source" : "engine",
					"targetIndexes" : 
					[
						1
					]
				}
			],
			"name" : "Debug",
			"projects" : 
			[
				{
					"childIndexes" : 
					[
						1,
						2
					],
					"directoryIndexes" : 
					[
						0
					],
					"name" : "vulkan_dev_env"
				},
				{
					"directoryIndexes" : 
					[
						1
					],
					"name" : "vulkan_application",
					"parentIndex" : 0,
					"targetIndexes" : 
					[
						0
					]
				},
				{
					"directoryIndexes" : 
					[
						2
					],
					"name" : "vulkan_engine",
					"parentIndex" : 0,
					"targetIndexes" : 
					[
						1
					]
				}
			],
			"targets" : 
			[
				{
					"directoryIndex" : 1,
					"id" : "vulkan_application::@5f5a17c01335469806cb",
					"jsonFile" : "target-vulkan_application-Debug-ac849442cb9eb95e14d8.json",
					"name" : "vulkan_application",
					"projectIndex" : 1
				},
				{
					"directoryIndex" : 2,
					"id" : "vulkan_engine::@4088515cb4035b412499",
					"jsonFile" : "target-vulkan_engine-Debug-9e1cdd20221f75730973.json",
					"name" : "vulkan_engine",
					"projectIndex" : 2
				}
			]
		}
	],
	"kind" : "codemodel",
	"paths" : 
	{
		"build" : "C:/dev/vulkan_engine/cmake-build-debug",
		"source" : "C:/dev/vulkan_engine"
	},
	"version" : 
	{
		"major" : 2,
		"minor" : 4
	}
}
